pyramid2_calc/__init__.py
pyramid2_calc/pyramid2_calc.py
pyramid2_calc-0.1.0.dist-info/METADATA
pyramid2_calc-0.1.0.dist-info/WHEEL
pyramid2_calc-0.1.0.dist-info/top_level.txt
pyramid2_calc-0.1.0.dist-info/RECORD
