Metadata-Version: 2.4
Name: pyramid2_calc
Version: 0.1.0
Summary: Execute ELF files and calculate the result
Home-page: https://github.com/Vornsk/pyramid2_calc
Author: Vornsk
Author-email: kangcori@email.com
Classifier: Programming Language :: Python :: 3
Classifier: License :: OSI Approved :: MIT License
Classifier: Operating System :: OS Independent
Requires-Python: >=3.7
Dynamic: author
Dynamic: author-email
Dynamic: classifier
Dynamic: description
Dynamic: description-content-type
Dynamic: home-page
Dynamic: requires-python
Dynamic: summary
